{
  "type": "FeatureCollection",
  "features": [
    {
      "type": "Feature",
      "properties": {
        "FID": 11,
        "area_km2": 77.62621568777384
      },
      "geometry": {
        "type": "Polygon",
        "coordinates": [
          [
            [
              14.330168261864415,
              55.972621621686606
            ],
            [
              14.354220629448065,
              55.98240956100625
            ],
            [
              14.43023877900103,
              56.01694727932403
            ],
            [
              14.46647828967636,
              56.049332056819736
            ],
            [
              14.503209855389343,
              56.046655377410644
            ],
            [
              14.52795604473738,
              56.06448262206851
            ],
            [
              14.54710781490735,
              56.07160613118924
            ],
            [
              14.567076385316653,
              56.06047243092871
            ],
            [
              14.567092811203821,
              56.04487241545658
            ],
            [
              14.59325427648659,
              56.061959774269326
            ],
            [
              14.624931428948656,
              56.06590128503939
            ],
            [
              14.631970804607505,
              56.05580085252251
            ],
            [
              14.614868743229891,
              56.0327841317762
            ],
            [
              14.601306828146193,
              56.02548259962782
            ],
            [
              14.589752810323716,
              56.009186182735476
            ],
            [
              14.573669764881373,
              56.01536726677847
            ],
            [
              14.550550387060014,
              56.01031008976469
            ],
            [
              14.541001078828316,
              56.024356168993904
            ],
            [
              14.543011459508335,
              56.031096472643355
            ],
            [
              14.542510371308566,
              56.04850310868176
            ],
            [
              14.527431009237574,
              56.031096472643355
            ],
            [
              14.495264918353968,
              56.026603067633005
            ],
            [
              14.476671491863613,
              56.02969267303561
            ],
            [
              14.4751691146501,
              56.021268190854954
            ],
            [
              14.475166736686447,
              56.008907142187326
            ],
            [
              14.453549519239715,
              55.99119922306869
            ],
            [
              14.414650421692045,
              55.962612917953464
            ],
            [
              14.352341373696419,
              55.95107980875579
            ],
            [
              14.336512283803927,
              55.94122048052489
            ],
            [
              14.33701521702207,
              55.91502307697931
            ],
            [
              14.330168261864415,
              55.91142701574317
            ],
            [
              14.330168261864415,
              55.972621621686606
            ]
          ]
        ]
      }
    }
  ]
}